notebooks/__init__.py
phisher/__init__.py
phisher/dataset/__init__.py
phisher/dataset/phishing_data_module.py
phisher/dataset/phishing_dataset.py
phisher/dataset/phishing_embeddings_dataset.py
phisher/dataset/phishing_one_hot_dataset.py
phisher/dataset/utils.py
phisher/model/__init__.py
phisher/model/phisher_embeddings_model.py
phisher/model/phisher_model.py
phisher/model/phisher_one_hot_model.py
phisher/module/__init__.py
phisher/module/phisher_module.py
phisher/xai/__init__.py
phisher/xai/gradcam.py
phisher/xai/phish_lime.py
phisher-0.1.1.dist-info/LICENSE
phisher-0.1.1.dist-info/METADATA
phisher-0.1.1.dist-info/WHEEL
phisher-0.1.1.dist-info/top_level.txt
phisher-0.1.1.dist-info/RECORD
