Metadata-Version: 2.1
Name: phisher
Version: 0.1.1
Summary: Phish Classificator based on URL
Home-page: https://github.com/Bartolo72/phisher
Author: WUT
License: MIT
Platform: UNKNOWN
Classifier: Programming Language :: Python :: 3
Classifier: License :: OSI Approved :: MIT License
Classifier: Operating System :: OS Independent
License-File: LICENSE
